doi2bibtex/__init__.py
doi2bibtex/ads.py
doi2bibtex/bibtex.py
doi2bibtex/cli.py
doi2bibtex/config.py
doi2bibtex/constants.py
doi2bibtex/dblp.py
doi2bibtex/identify.py
doi2bibtex/isbn.py
doi2bibtex/process.py
doi2bibtex/resolve.py
doi2bibtex/utils.py
doi2bibtex-0.2.0.dist-info/LICENSE
doi2bibtex-0.2.0.dist-info/METADATA
doi2bibtex-0.2.0.dist-info/WHEEL
doi2bibtex-0.2.0.dist-info/entry_points.txt
doi2bibtex-0.2.0.dist-info/top_level.txt
doi2bibtex-0.2.0.dist-info/RECORD
