Metadata-Version: 2.1
Name: doi2bibtex
Version: 0.2.0
Summary: Resolve DOIs and arXiv identifiers to formatted BibTeX entries
Home-page: https://github.com/timothygebhard/doi2bibtex
Author: Timothy Gebhard
Classifier: License :: OSI Approved :: BSD License
Classifier: Development Status :: 4 - Beta
Classifier: Programming Language :: Python :: 3
Classifier: Programming Language :: Python :: 3.8
Classifier: Programming Language :: Python :: 3.9
Classifier: Programming Language :: Python :: 3.10
Classifier: Programming Language :: Python :: 3.11
Classifier: Intended Audience :: Developers
Classifier: Intended Audience :: Science/Research
License-File: LICENSE
Requires-Dist: beautifulsoup4
Requires-Dist: bibtexparser
Requires-Dist: isbnlib
Requires-Dist: pylatexenc
Requires-Dist: pyyaml
Requires-Dist: requests
Requires-Dist: rich
Requires-Dist: unidecode
Provides-Extra: develop
Requires-Dist: coverage ; extra == 'develop'
Requires-Dist: deepdiff ; extra == 'develop'
Requires-Dist: flake8 ; extra == 'develop'
Requires-Dist: mypy ; extra == 'develop'
Requires-Dist: pytest ; extra == 'develop'
Requires-Dist: pytest-cov ; extra == 'develop'
Requires-Dist: pytest-mock ; extra == 'develop'
Requires-Dist: types-beautifulsoup4 ; extra == 'develop'
Requires-Dist: types-PyYAML ; extra == 'develop'
Requires-Dist: types-requests ; extra == 'develop'
Requires-Dist: types-setuptools ; extra == 'develop'
